fugashi/__init__.py
fugashi/cli.py
fugashi/fugashi.cpython-311-darwin.so
fugashi/.dylibs/libmecab.2.dylib
fugashi-1.5.1.dist-info/RECORD
fugashi-1.5.1.dist-info/WHEEL
fugashi-1.5.1.dist-info/entry_points.txt
fugashi-1.5.1.dist-info/top_level.txt
fugashi-1.5.1.dist-info/METADATA
fugashi-1.5.1.dist-info/licenses/LICENSE
fugashi-1.5.1.dist-info/licenses/LICENSE.mecab
