Metadata-Version: 2.4
Name: fugashi
Version: 1.5.1
Summary: Cython MeCab wrapper for fast, pythonic Japanese tokenization.
Author-email: Paul O'Leary McCann <polm@dampfkraft.com>
License-Expression: MIT AND BSD-3-Clause
Project-URL: source, https://github.com/polm/fugashi
Project-URL: funding, https://github.com/sponsors/polm
Classifier: Environment :: Console
Classifier: Intended Audience :: Developers
Classifier: Intended Audience :: Science/Research
Classifier: Natural Language :: Japanese
Classifier: Operating System :: POSIX :: Linux
Classifier: Operating System :: MacOS :: MacOS X
Classifier: Programming Language :: Cython
Classifier: Programming Language :: Python :: 3
Classifier: Topic :: Text Processing :: Linguistic
Requires-Python: >=3.9
License-File: LICENSE
License-File: LICENSE.mecab
Provides-Extra: unidic
Requires-Dist: unidic; extra == "unidic"
Provides-Extra: unidic-lite
Requires-Dist: unidic-lite; extra == "unidic-lite"
Dynamic: license-file
